aiohttp_hijacks/__init__.py
aiohttp_hijacks/_version.py
aiohttp_hijacks/server.py
aiohttp_hijacks-0.0.1.dist-info/METADATA
aiohttp_hijacks-0.0.1.dist-info/WHEEL
aiohttp_hijacks-0.0.1.dist-info/top_level.txt
aiohttp_hijacks-0.0.1.dist-info/RECORD
