Metadata-Version: 2.1
Name: aiohttp-hijacks
Version: 0.0.1
Summary: Re-route aiohttp session requests. Usefull for testing.
Home-page: https://gitlab.com/cdlr75/aiohttp-hijacks
Author: cdlr75
Author-email: cdlr75@gmail.com
License: UNKNOWN
Project-URL: Bug Reports, https://gitlab.com/cdlr75/aiohttp-hijacks/issues
Project-URL: Source, https://gitlab.com/cdlr75/aiohttp-hijacks/
Keywords: aiohttp testing
Platform: UNKNOWN
Classifier: Development Status :: 3 - Alpha
Classifier: Intended Audience :: Developers
Classifier: Topic :: Software Development :: Build Tools
Classifier: License :: OSI Approved :: MIT License
Classifier: Programming Language :: Python :: 3
Classifier: Programming Language :: Python :: 3.5
Classifier: Programming Language :: Python :: 3.6
Classifier: Programming Language :: Python :: 3.7
Requires-Python: >=3
Requires-Dist: aiohttp
Provides-Extra: test
Requires-Dist: asynctest (==0.13.0) ; extra == 'test'
Requires-Dist: pytest (==6.2.2) ; extra == 'test'
Requires-Dist: pytest-cov (==2.11.1) ; extra == 'test'
